{
  "hash": "7d401238b4d022d5226baed6e9f07c7e",
  "result": {
    "engine": "knitr",
    "markdown": "---\ntitle: \"ANAVA de 1 critério (one-way ANOVA)\"\nformat: html\ntoc: true\ntoc-depth: 3\nnumber-sections: true\nlang: pt\n---\n\n|   A ANAVA, *\"Análise de Variância\"*, consiste num procedimento bastante usual em diversas áreas do conhecimento, quando se deseja avaliar se há ou não diferenças entre grupos testados num experimento. Nesse caso, dá-se a comparação pela medida da variação de erros entre grupos, e a variação encontrada dentro de cada grupo. \n|   Uma ANAVA pode ser conduzida para diversos tipos de planejamento experimental, sendo bastante comuns a ANAVA unidirecional (1 critério ou fator de variação, ou *one-way ANOVA*) e a ANAVA bidirecional (2 fatores de variação, ou *two-way ANOVA*).\n\n|   O programa *1ANAVA1matrix* calcula os parâmetros e *p-valor* para uma ANAVA unidirecional, bastando-se inserir uma matriz contendo os dados (vetores coluna).\n\n## Arquivos:\n\n1. [Programa 1ANAVA1matrix e exemplo](1ANAVA1matrix.zip)\n2. [Código do programa](1ANAVA1matrix.pdf)\n\\\n\n## Uso e exemplo\n\n\n\n::: {.cell}\n\n```{.r .cell-code}\n# Entrada:\n1. Matrix de dados (vetor coluna);\n2. \"1ANAVA1matrix\"\n\n# Saída:\n1. sqtr: soma dos quadrados do tratamento;\n2. sqr: soma dos quadrados dos resíduos;\n3. qmtr: quadrado médio do tratamento;\n4. qmr: quadrado médio do resíduo;\n5. F: valor da distribuição F de Snedecor;\n6. p: p-valor;\n7. R²: coeficiente de determinação.\n```\n:::\n\n\\\n\n|   O arquivo comprimido acompanha um exemplo de resultados de um ensaio randômico (Vieira, 2000, p. 39). \n\\\n\n::: {#fig-SimPlot layout-ncol=2}\n\n![Inserção de matrix de dados.](dados.jpeg){#fig-dados}\n\n\n![Resultados obtidos da ANAVA](result.jpeg){#fig-result}\n\nPrograma *1ANAVA1matrix* pela versão Android de HP50G ([Go49gp](https://sites.google.com/site/olivier2smet2/home/go49gp)), exibindo entrada de dados e resultados do exemplo.\n\n:::\n\\\n\n|   Os resultados obtidos coincidem com o da fonte (Sonia, 2000).\n\n\n## Referências:\n\n1. Vieira, Sônia. Análise de variância: ANOVA. Editora Atlas SA, 2000.\n",
    "supporting": [],
    "filters": [
      "rmarkdown/pagebreak.lua"
    ],
    "includes": {},
    "engineDependencies": {},
    "preserve": {},
    "postProcess": true
  }
}